terso/__init__.py
terso/cli.py
terso/client.py
terso/config.py
terso/datasets.py
terso/download.py
terso/py.typed
terso-0.2.0a2.dist-info/METADATA
terso-0.2.0a2.dist-info/WHEEL
terso-0.2.0a2.dist-info/entry_points.txt
terso-0.2.0a2.dist-info/RECORD
