Metadata-Version: 2.4
Name: terso
Version: 0.2.0a2
Summary: Deployment-ready data for physical AI
Project-URL: Homepage, https://terso.com
Project-URL: Documentation, https://docs.terso.com
Project-URL: Repository, https://github.com/tersoai/terso-py
Project-URL: Issues, https://github.com/tersoai/terso/issues
Author-email: Terso <dev@terso.com>
License: Proprietary
Keywords: datasets,hand-tracking,imitation-learning,manipulation,robotics
Classifier: Development Status :: 3 - Alpha
Classifier: Intended Audience :: Developers
Classifier: Intended Audience :: Science/Research
Classifier: License :: Other/Proprietary License
Classifier: Programming Language :: Python :: 3
Classifier: Programming Language :: Python :: 3.10
Classifier: Programming Language :: Python :: 3.11
Classifier: Programming Language :: Python :: 3.12
Classifier: Programming Language :: Python :: 3.13
Classifier: Topic :: Scientific/Engineering :: Artificial Intelligence
Classifier: Topic :: Scientific/Engineering :: Image Recognition
Requires-Python: >=3.10
Requires-Dist: datasets>=2.14.0
Requires-Dist: numpy>=1.24.0
Requires-Dist: requests>=2.28.0
Requires-Dist: tqdm>=4.60.0
Provides-Extra: dev
Requires-Dist: black>=23.9.0; extra == 'dev'
Requires-Dist: build>=1.0.0; extra == 'dev'
Requires-Dist: mypy>=1.5.0; extra == 'dev'
Requires-Dist: pytest-cov>=4.1.0; extra == 'dev'
Requires-Dist: pytest>=7.4.0; extra == 'dev'
Requires-Dist: ruff>=0.1.0; extra == 'dev'
Requires-Dist: twine>=4.0.0; extra == 'dev'
Provides-Extra: torch
Requires-Dist: torch>=2.0.0; extra == 'torch'
Requires-Dist: torchvision>=0.15.0; extra == 'torch'
Provides-Extra: viz
Requires-Dist: matplotlib>=3.7.0; extra == 'viz'
